DataPrepKit/DataPrepKit.py
DataPrepKit/__init__.py
DataPrepKit2Ahmed-0.1.dist-info/METADATA
DataPrepKit2Ahmed-0.1.dist-info/WHEEL
DataPrepKit2Ahmed-0.1.dist-info/top_level.txt
DataPrepKit2Ahmed-0.1.dist-info/RECORD
